exheader.py
exheader-0.0.1.dist-info/LICENSE
exheader-0.0.1.dist-info/METADATA
exheader-0.0.1.dist-info/WHEEL
exheader-0.0.1.dist-info/top_level.txt
exheader-0.0.1.dist-info/RECORD
