Metadata-Version: 2.1
Name: exheader
Version: 0.0.1
Summary: Library for handling 3ds exheader files
Home-page: UNKNOWN
License: UNKNOWN
Platform: UNKNOWN
Classifier: Programming Language :: Python :: 3
Classifier: License :: OSI Approved :: MIT License
Classifier: Operating System :: OS Independent
